teamly/__init__.py
teamly/abc.py
teamly/announcement.py
teamly/application.py
teamly/blog.py
teamly/cache.py
teamly/channel.py
teamly/client.py
teamly/color.py
teamly/embed.py
teamly/enums.py
teamly/gateway.py
teamly/http.py
teamly/logging.py
teamly/member.py
teamly/message.py
teamly/reaction.py
teamly/role.py
teamly/state.py
teamly/team.py
teamly/todo.py
teamly/user.py
teamly/utils.py
teamly/types/announcement.py
teamly/types/application.py
teamly/types/blog.py
teamly/types/channel.py
teamly/types/embed.py
teamly/types/member.py
teamly/types/message.py
teamly/types/reaction.py
teamly/types/role.py
teamly/types/team.py
teamly/types/todo.py
teamly/types/user.py
teamly_py-0.1.0a2.dist-info/licenses/LICENSE
teamly_py-0.1.0a2.dist-info/METADATA
teamly_py-0.1.0a2.dist-info/WHEEL
teamly_py-0.1.0a2.dist-info/top_level.txt
teamly_py-0.1.0a2.dist-info/RECORD
