Metadata-Version: 2.4
Name: teamly.py
Version: 0.1.0a2
Summary: Teamly API wrapper for bots and automation
Author: MrFatihLD
License-Expression: MIT
Project-URL: Homepage, https://github.com/MrFatihLD/teamly.py.git
Requires-Python: >=3.8
License-File: LICENSE
Requires-Dist: aiohttp>=3.8.0
Requires-Dist: loguru>=0.7.0
Dynamic: license-file
